odoo/addons/contract_transmit_method/README.rst
odoo/addons/contract_transmit_method/__init__.py
odoo/addons/contract_transmit_method/__manifest__.py
odoo/addons/contract_transmit_method/i18n/contract_transmit_method.pot
odoo/addons/contract_transmit_method/models/__init__.py
odoo/addons/contract_transmit_method/models/contract_abstract.py
odoo/addons/contract_transmit_method/models/contract_contract.py
odoo/addons/contract_transmit_method/readme/CONTRIBUTORS.rst
odoo/addons/contract_transmit_method/readme/DESCRIPTION.rst
odoo/addons/contract_transmit_method/static/description/icon.png
odoo/addons/contract_transmit_method/static/description/index.html
odoo/addons/contract_transmit_method/tests/__init__.py
odoo/addons/contract_transmit_method/tests/test_contract.py
odoo/addons/contract_transmit_method/views/contract_contract.xml
odoo/addons/contract_transmit_method/views/contract_template.xml
odoo12_addon_contract_transmit_method-12.0.1.1.0.dist-info/METADATA
odoo12_addon_contract_transmit_method-12.0.1.1.0.dist-info/WHEEL
odoo12_addon_contract_transmit_method-12.0.1.1.0.dist-info/top_level.txt
odoo12_addon_contract_transmit_method-12.0.1.1.0.dist-info/RECORD
