Metadata-Version: 2.1
Name: odoo12-addon-contract-transmit-method
Version: 12.0.1.1.0
Summary: Set transmit method (email, post, portal, ...) in contracts and propagate it to invoices.
Home-page: https://github.com/OCA/contract
Author: ACSONE SA/NV,Odoo Community Association (OCA)
Author-email: support@odoo-community.org
License: AGPL-3
Platform: UNKNOWN
Classifier: Programming Language :: Python
Classifier: Framework :: Odoo
Classifier: License :: OSI Approved :: GNU Affero General Public License v3
Requires-Python: >=3.5
Requires-Dist: odoo12-addon-account-invoice-transmit-method
Requires-Dist: odoo12-addon-contract
Requires-Dist: odoo (<12.1dev,>=12.0a)
